README.md
setup.py
fishervector/FisherVector.py
fishervector/__init__.py
fishervector.egg-info/PKG-INFO
fishervector.egg-info/SOURCES.txt
fishervector.egg-info/dependency_links.txt
fishervector.egg-info/not-zip-safe
fishervector.egg-info/requires.txt
fishervector.egg-info/top_level.txt