Metadata-Version: 1.0
Name: fishervector
Version: 0.1
Summary: Fisher Vectors based on Gaussian Mixture Model
Home-page: https://github.com/jonasrothfuss/py-fisher-vector
Author: Jonas Rothfuss, Fabio Ferreira
Author-email: jonas.rothfuss@gmail.com
License: MIT
Platform: UNKNOWN
